AUTHORS.rst
CONTRIBUTING.rst
HISTORY.rst
LICENSE
MANIFEST.in
README.rst
setup.cfg
setup.py
docs/Makefile
docs/authors.rst
docs/conf.py
docs/contributing.rst
docs/history.rst
docs/index.rst
docs/installation.rst
docs/make.bat
docs/modules.rst
docs/readme.rst
docs/usage.rst
docs/_build/html/_static/ajax-loader.gif
docs/_build/html/_static/comment-bright.png
docs/_build/html/_static/comment-close.png
docs/_build/html/_static/comment.png
docs/_build/html/_static/down-pressed.png
docs/_build/html/_static/down.png
docs/_build/html/_static/file.png
docs/_build/html/_static/minus.png
docs/_build/html/_static/plus.png
docs/_build/html/_static/up-pressed.png
docs/_build/html/_static/up.png
sec_edgar_download/__init__.py
sec_edgar_download/cli.py
sec_edgar_download/indexer.py
sec_edgar_download.egg-info/PKG-INFO
sec_edgar_download.egg-info/SOURCES.txt
sec_edgar_download.egg-info/dependency_links.txt
sec_edgar_download.egg-info/entry_points.txt
sec_edgar_download.egg-info/not-zip-safe
sec_edgar_download.egg-info/requires.txt
sec_edgar_download.egg-info/top_level.txt
tests/__init__.py
tests/intc-20151226.xml
tests/test_sec_edgar_download.py
tests/xbrlrss-2016-12.xml