Metadata-Version: 1.1
Name: sec-edgar-download
Version: 0.1.1
Summary: Downloads sec xbrl filings
Home-page: https://github.com/robren/sec_edgar_download
Author: Robert Rennison
Author-email: rob@robren.net
License: Apache Software License 2.0
Keywords: sec_edgar_download
Platform: UNKNOWN
Classifier: Development Status :: 2 - Pre-Alpha
Classifier: Intended Audience :: Developers
Classifier: License :: OSI Approved :: Apache Software License
Classifier: Natural Language :: English
Classifier: Programming Language :: Python :: 2.7
Classifier: Programming Language :: Python :: 3
Classifier: Programming Language :: Python :: 3.4
Classifier: Programming Language :: Python :: 3.5
Classifier: Programming Language :: Python :: 3.6
